transportforlondon/__init__.py
transportforlondon/bikepoint.py
transportforlondon/busservice.py
transportforlondon/core.py
transportforlondon/places.py
tfl_bsdprof-0.1.dist-info/COPYING
tfl_bsdprof-0.1.dist-info/LICENSE
tfl_bsdprof-0.1.dist-info/METADATA
tfl_bsdprof-0.1.dist-info/WHEEL
tfl_bsdprof-0.1.dist-info/top_level.txt
tfl_bsdprof-0.1.dist-info/RECORD
