Metadata-Version: 2.1
Name: tfl-bsdprof
Version: 0.1
Summary: A Python wrapper for the Unified API of the Transport for London
Home-page: https://github.com/raulmarinperez/transportforlondon
Author: The BSD Professor
Author-email: me@bsdprof.com
License: UNKNOWN
Project-URL: Bug Tracker, https://github.com/raulmarinperez/transportforlondon/issues
Platform: UNKNOWN
Classifier: Programming Language :: Python :: 3
Classifier: License :: OSI Approved :: MIT License
Classifier: Operating System :: OS Independent
Requires-Python: >=3.7
Requires-Dist: requests
